[
  {
    "corp_code": "00317487",
    "corp_name": "티에스넥스젠",
    "stock_code": "043220",
    "corp_cls": "K",
    "report_nm": "주권매매거래정지              (투자자 보호)",
    "rcept_no": "20260609900542",
    "flr_nm": "코스닥시장본부",
    "rcept_dt": "20260609",
    "rm": "코"
  },
  {
    "corp_code": "00317487",
    "corp_name": "티에스넥스젠",
    "stock_code": "043220",
    "corp_cls": "K",
    "report_nm": "기타시장안내              (정리매매 보류 관련)",
    "rcept_no": "20260609900536",
    "flr_nm": "코스닥시장본부",
    "rcept_dt": "20260609",
    "rm": "코"
  },
  {
    "corp_code": "00317487",
    "corp_name": "티에스넥스젠",
    "stock_code": "043220",
    "corp_cls": "K",
    "report_nm": "기타경영사항(자율공시)              (상장폐지결정 효력정지 가처분 신청)",
    "rcept_no": "20260609900527",
    "flr_nm": "티에스넥스젠",
    "rcept_dt": "20260609",
    "rm": "코"
  },
  {
    "corp_code": "00317487",
    "corp_name": "티에스넥스젠",
    "stock_code": "043220",
    "corp_cls": "K",
    "report_nm": "주권매매거래정지해제              (상장폐지에 따른 정리매매 개시)",
    "rcept_no": "20260608901053",
    "flr_nm": "코스닥시장본부",
    "rcept_dt": "20260608",
    "rm": "코"
  },
  {
    "corp_code": "00317487",
    "corp_name": "티에스넥스젠",
    "stock_code": "043220",
    "corp_cls": "K",
    "report_nm": "기타시장안내              (기업심사위원회 심의·의결 결과 안내)",
    "rcept_no": "20260608901046",
    "flr_nm": "코스닥시장본부",
    "rcept_dt": "20260608",
    "rm": "코"
  },
  {
    "corp_code": "00317487",
    "corp_name": "티에스넥스젠",
    "stock_code": "043220",
    "corp_cls": "K",
    "report_nm": "전환청구권행사              (제12회차)",
    "rcept_no": "20260604900340",
    "flr_nm": "티에스넥스젠",
    "rcept_dt": "20260604",
    "rm": "코"
  },
  {
    "corp_code": "00317487",
    "corp_name": "티에스넥스젠",
    "stock_code": "043220",
    "corp_cls": "K",
    "report_nm": "기타시장안내              (개선계획서 제출)",
    "rcept_no": "20260522900507",
    "flr_nm": "코스닥시장본부",
    "rcept_dt": "20260522",
    "rm": "코"
  },
  {
    "corp_code": "00317487",
    "corp_name": "티에스넥스젠",
    "stock_code": "043220",
    "corp_cls": "K",
    "report_nm": "주권매매거래정지기간변경              (회생절차 개시신청)",
    "rcept_no": "20260520900789",
    "flr_nm": "코스닥시장본부",
    "rcept_dt": "20260520",
    "rm": "코"
  },
  {
    "corp_code": "00317487",
    "corp_name": "티에스넥스젠",
    "stock_code": "043220",
    "corp_cls": "K",
    "report_nm": "주요사항보고서(회생절차개시신청)",
    "rcept_no": "20260520000394",
    "flr_nm": "티에스넥스젠",
    "rcept_dt": "20260520",
    "rm": ""
  },
  {
    "corp_code": "00317487",
    "corp_name": "티에스넥스젠",
    "stock_code": "043220",
    "corp_cls": "K",
    "report_nm": "분기보고서 (2026.03)",
    "rcept_no": "20260515001328",
    "flr_nm": "티에스넥스젠",
    "rcept_dt": "20260515",
    "rm": ""
  },
  {
    "corp_code": "00317487",
    "corp_name": "티에스넥스젠",
    "stock_code": "043220",
    "corp_cls": "K",
    "report_nm": "기타시장안내              (개선계획 이행내역서 제출에 따른 안내)",
    "rcept_no": "20260512900809",
    "flr_nm": "코스닥시장본부",
    "rcept_dt": "20260512",
    "rm": "코"
  },
  {
    "corp_code": "00317487",
    "corp_name": "티에스넥스젠",
    "stock_code": "043220",
    "corp_cls": "K",
    "report_nm": "소송등의판결ㆍ결정(일정금액이상의청구)              ",
    "rcept_no": "20260507901044",
    "flr_nm": "티에스넥스젠",
    "rcept_dt": "20260507",
    "rm": "코"
  },
  {
    "corp_code": "00317487",
    "corp_name": "티에스넥스젠",
    "stock_code": "043220",
    "corp_cls": "K",
    "report_nm": "주권매매거래정지기간변경              (상장적격성 실질심사 대상 결정)",
    "rcept_no": "20260429901144",
    "flr_nm": "코스닥시장본부",
    "rcept_dt": "20260429",
    "rm": "코"
  },
  {
    "corp_code": "00317487",
    "corp_name": "티에스넥스젠",
    "stock_code": "043220",
    "corp_cls": "K",
    "report_nm": "기타시장안내              (상장적격성 실질심사 대상 결정)",
    "rcept_no": "20260429900628",
    "flr_nm": "코스닥시장본부",
    "rcept_dt": "20260429",
    "rm": "코"
  },
  {
    "corp_code": "00317487",
    "corp_name": "티에스넥스젠",
    "stock_code": "043220",
    "corp_cls": "K",
    "report_nm": "[기재정정]기타시장안내              (상장폐지 관련 이의신청서 접수)",
    "rcept_no": "20260429900131",
    "flr_nm": "코스닥시장본부",
    "rcept_dt": "20260429",
    "rm": "코"
  },
  {
    "corp_code": "00317487",
    "corp_name": "티에스넥스젠",
    "stock_code": "043220",
    "corp_cls": "K",
    "report_nm": "[기재정정]기타시장안내              (개선기간 종료에 따른 상장폐지 여부 결정 안내)",
    "rcept_no": "20260429900129",
    "flr_nm": "코스닥시장본부",
    "rcept_dt": "20260429",
    "rm": "코"
  },
  {
    "corp_code": "00317487",
    "corp_name": "티에스넥스젠",
    "stock_code": "043220",
    "corp_cls": "K",
    "report_nm": "기타시장안내              (상장폐지 관련 이의신청서 접수)",
    "rcept_no": "20260428900832",
    "flr_nm": "코스닥시장본부",
    "rcept_dt": "20260428",
    "rm": "코정"
  },
  {
    "corp_code": "00317487",
    "corp_name": "티에스넥스젠",
    "stock_code": "043220",
    "corp_cls": "K",
    "report_nm": "기타시장안내              (개선기간 종료에 따른 상장폐지 여부 결정 안내)",
    "rcept_no": "20260410901040",
    "flr_nm": "코스닥시장본부",
    "rcept_dt": "20260410",
    "rm": "코정"
  },
  {
    "corp_code": "00317487",
    "corp_name": "티에스넥스젠",
    "stock_code": "043220",
    "corp_cls": "K",
    "report_nm": "기타시장안내              (실질심사 대상여부 결정을 위한 조사기간 연장 안내)",
    "rcept_no": "20260409900877",
    "flr_nm": "코스닥시장본부",
    "rcept_dt": "20260409",
    "rm": "코"
  },
  {
    "corp_code": "00317487",
    "corp_name": "티에스넥스젠",
    "stock_code": "043220",
    "corp_cls": "K",
    "report_nm": "주권매매거래정지기간변경              (상장폐지 사유 발생)",
    "rcept_no": "20260407901234",
    "flr_nm": "코스닥시장본부",
    "rcept_dt": "20260407",
    "rm": "코"
  },
  {
    "corp_code": "00317487",
    "corp_name": "티에스넥스젠",
    "stock_code": "043220",
    "corp_cls": "K",
    "report_nm": "기타시장안내              (상장폐지 관련)",
    "rcept_no": "20260407901231",
    "flr_nm": "코스닥시장본부",
    "rcept_dt": "20260407",
    "rm": "코"
  },
  {
    "corp_code": "00317487",
    "corp_name": "티에스넥스젠",
    "stock_code": "043220",
    "corp_cls": "K",
    "report_nm": "감사보고서제출              ",
    "rcept_no": "20260407901131",
    "flr_nm": "티에스넥스젠",
    "rcept_dt": "20260407",
    "rm": "코"
  },
  {
    "corp_code": "00317487",
    "corp_name": "티에스넥스젠",
    "stock_code": "043220",
    "corp_cls": "K",
    "report_nm": "사업보고서 (2025.12)",
    "rcept_no": "20260407003639",
    "flr_nm": "티에스넥스젠",
    "rcept_dt": "20260407",
    "rm": "연"
  },
  {
    "corp_code": "00317487",
    "corp_name": "티에스넥스젠",
    "stock_code": "043220",
    "corp_cls": "K",
    "report_nm": "정기주주총회결과              ",
    "rcept_no": "20260331904785",
    "flr_nm": "티에스넥스젠",
    "rcept_dt": "20260331",
    "rm": "코"
  },
  {
    "corp_code": "00317487",
    "corp_name": "티에스넥스젠",
    "stock_code": "043220",
    "corp_cls": "K",
    "report_nm": "사업보고서제출기한연장신고서 (2025.12)",
    "rcept_no": "20260323000937",
    "flr_nm": "티에스넥스젠",
    "rcept_dt": "20260323",
    "rm": ""
  },
  {
    "corp_code": "00317487",
    "corp_name": "티에스넥스젠",
    "stock_code": "043220",
    "corp_cls": "K",
    "report_nm": "기타경영사항(자율공시)              (감사보고서 제출 지연)",
    "rcept_no": "20260323900414",
    "flr_nm": "티에스넥스젠",
    "rcept_dt": "20260323",
    "rm": "코"
  },
  {
    "corp_code": "00317487",
    "corp_name": "티에스넥스젠",
    "stock_code": "043220",
    "corp_cls": "K",
    "report_nm": "기타시장안내              (상장적격성 실질심사 대상결정 기한 안내)",
    "rcept_no": "20260320900147",
    "flr_nm": "코스닥시장본부",
    "rcept_dt": "20260320",
    "rm": "코"
  },
  {
    "corp_code": "00317487",
    "corp_name": "티에스넥스젠",
    "stock_code": "043220",
    "corp_cls": "K",
    "report_nm": "[기재정정]기타시장안내              (상장적격성 실질심사 관련 안내)",
    "rcept_no": "20260320900158",
    "flr_nm": "코스닥시장본부",
    "rcept_dt": "20260320",
    "rm": "코"
  },
  {
    "corp_code": "00317487",
    "corp_name": "티에스넥스젠",
    "stock_code": "043220",
    "corp_cls": "K",
    "report_nm": "기타시장안내              (상장적격성 실질심사 관련 안내)",
    "rcept_no": "20260319902175",
    "flr_nm": "코스닥시장본부",
    "rcept_dt": "20260319",
    "rm": "코정"
  },
  {
    "corp_code": "00317487",
    "corp_name": "티에스넥스젠",
    "stock_code": "043220",
    "corp_cls": "K",
    "report_nm": "주권매매거래정지기간변경              (상장적격성 실질심사 대상 (사유발생))",
    "rcept_no": "20260319902174",
    "flr_nm": "코스닥시장본부",
    "rcept_dt": "20260319",
    "rm": "코"
  },
  {
    "corp_code": "00317487",
    "corp_name": "티에스넥스젠",
    "stock_code": "043220",
    "corp_cls": "K",
    "report_nm": "최대주주변경              ",
    "rcept_no": "20260319902173",
    "flr_nm": "티에스넥스젠",
    "rcept_dt": "20260319",
    "rm": "코"
  },
  {
    "corp_code": "00317487",
    "corp_name": "티에스넥스젠",
    "stock_code": "043220",
    "corp_cls": "K",
    "report_nm": "주식등의대량보유상황보고서(일반)",
    "rcept_no": "20260319000883",
    "flr_nm": "시스코바이오투자조합",
    "rcept_dt": "20260319",
    "rm": ""
  },
  {
    "corp_code": "00317487",
    "corp_name": "티에스넥스젠",
    "stock_code": "043220",
    "corp_cls": "K",
    "report_nm": "의결권대리행사권유참고서류",
    "rcept_no": "20260316000296",
    "flr_nm": "티에스넥스젠",
    "rcept_dt": "20260316",
    "rm": ""
  },
  {
    "corp_code": "00317487",
    "corp_name": "티에스넥스젠",
    "stock_code": "043220",
    "corp_cls": "K",
    "report_nm": "주주총회소집공고",
    "rcept_no": "20260316000292",
    "flr_nm": "티에스넥스젠",
    "rcept_dt": "20260316",
    "rm": ""
  },
  {
    "corp_code": "00317487",
    "corp_name": "티에스넥스젠",
    "stock_code": "043220",
    "corp_cls": "K",
    "report_nm": "주주총회소집결의              ",
    "rcept_no": "20260316900292",
    "flr_nm": "티에스넥스젠",
    "rcept_dt": "20260316",
    "rm": "코"
  },
  {
    "corp_code": "00317487",
    "corp_name": "티에스넥스젠",
    "stock_code": "043220",
    "corp_cls": "K",
    "report_nm": "매출액또는손익구조30%(대규모법인은15%)이상변동              ",
    "rcept_no": "20260227902202",
    "flr_nm": "티에스넥스젠",
    "rcept_dt": "20260227",
    "rm": "코"
  },
  {
    "corp_code": "00317487",
    "corp_name": "티에스넥스젠",
    "stock_code": "043220",
    "corp_cls": "K",
    "report_nm": "소송등의제기ㆍ신청(일정금액이상의청구)              ",
    "rcept_no": "20251230900556",
    "flr_nm": "티에스넥스젠",
    "rcept_dt": "20251230",
    "rm": "코"
  },
  {
    "corp_code": "00317487",
    "corp_name": "티에스넥스젠",
    "stock_code": "043220",
    "corp_cls": "K",
    "report_nm": "[기재정정]단일판매ㆍ공급계약체결              ",
    "rcept_no": "20251224900847",
    "flr_nm": "티에스넥스젠",
    "rcept_dt": "20251224",
    "rm": "코"
  },
  {
    "corp_code": "00317487",
    "corp_name": "티에스넥스젠",
    "stock_code": "043220",
    "corp_cls": "K",
    "report_nm": "본점소재지변경              ",
    "rcept_no": "20251222900240",
    "flr_nm": "티에스넥스젠",
    "rcept_dt": "20251222",
    "rm": "코"
  },
  {
    "corp_code": "00317487",
    "corp_name": "티에스넥스젠",
    "stock_code": "043220",
    "corp_cls": "K",
    "report_nm": "주주명부폐쇄기간또는기준일설정              ",
    "rcept_no": "20251216900478",
    "flr_nm": "티에스넥스젠",
    "rcept_dt": "20251216",
    "rm": "코"
  },
  {
    "corp_code": "00317487",
    "corp_name": "티에스넥스젠",
    "stock_code": "043220",
    "corp_cls": "K",
    "report_nm": "주권매매거래정지기간변경              (감자 주권 변경상장)",
    "rcept_no": "20251204900472",
    "flr_nm": "코스닥시장본부",
    "rcept_dt": "20251204",
    "rm": "코"
  },
  {
    "corp_code": "00317487",
    "corp_name": "티에스넥스젠",
    "stock_code": "043220",
    "corp_cls": "K",
    "report_nm": "감자완료              ",
    "rcept_no": "20251124900344",
    "flr_nm": "티에스넥스젠",
    "rcept_dt": "20251124",
    "rm": "코"
  },
  {
    "corp_code": "00317487",
    "corp_name": "티에스넥스젠",
    "stock_code": "043220",
    "corp_cls": "K",
    "report_nm": "분기보고서 (2025.09)",
    "rcept_no": "20251114001067",
    "flr_nm": "티에스넥스젠",
    "rcept_dt": "20251114",
    "rm": ""
  },
  {
    "corp_code": "00317487",
    "corp_name": "티에스넥스젠",
    "stock_code": "043220",
    "corp_cls": "K",
    "report_nm": "주권매매거래정지기간변경              (주식의 병합, 분할 등 전자등록 변경, 말소)",
    "rcept_no": "20251112900595",
    "flr_nm": "코스닥시장본부",
    "rcept_dt": "20251112",
    "rm": "코"
  },
  {
    "corp_code": "00317487",
    "corp_name": "티에스넥스젠",
    "stock_code": "043220",
    "corp_cls": "K",
    "report_nm": "주식등의대량보유상황보고서(약식)",
    "rcept_no": "20251030000185",
    "flr_nm": "바로저축은행",
    "rcept_dt": "20251030",
    "rm": ""
  },
  {
    "corp_code": "00317487",
    "corp_name": "티에스넥스젠",
    "stock_code": "043220",
    "corp_cls": "K",
    "report_nm": "불성실공시법인지정              (공시번복)",
    "rcept_no": "20251029900743",
    "flr_nm": "코스닥시장본부",
    "rcept_dt": "20251029",
    "rm": "코"
  },
  {
    "corp_code": "00317487",
    "corp_name": "티에스넥스젠",
    "stock_code": "043220",
    "corp_cls": "K",
    "report_nm": "신주인수권부사채(해외신주인수권부사채포함)발행후만기전사채취득              (제16회차)",
    "rcept_no": "20251027900653",
    "flr_nm": "티에스넥스젠",
    "rcept_dt": "20251027",
    "rm": "코"
  },
  {
    "corp_code": "00317487",
    "corp_name": "티에스넥스젠",
    "stock_code": "043220",
    "corp_cls": "K",
    "report_nm": "소송등의판결ㆍ결정(일정금액이상의청구)              (신탁수익권 등 가압류)",
    "rcept_no": "20251024900641",
    "flr_nm": "티에스넥스젠",
    "rcept_dt": "20251024",
    "rm": "코"
  },
  {
    "corp_code": "00317487",
    "corp_name": "티에스넥스젠",
    "stock_code": "043220",
    "corp_cls": "K",
    "report_nm": "소송등의판결ㆍ결정              (임시총회소집허가 신청 취하)",
    "rcept_no": "20251022900220",
    "flr_nm": "티에스넥스젠",
    "rcept_dt": "20251022",
    "rm": "코"
  },
  {
    "corp_code": "00317487",
    "corp_name": "티에스넥스젠",
    "stock_code": "043220",
    "corp_cls": "K",
    "report_nm": "임시주주총회결과              ",
    "rcept_no": "20251016900299",
    "flr_nm": "티에스넥스젠",
    "rcept_dt": "20251016",
    "rm": "코"
  },
  {
    "corp_code": "00317487",
    "corp_name": "티에스넥스젠",
    "stock_code": "043220",
    "corp_cls": "K",
    "report_nm": "임시주주총회결과              ",
    "rcept_no": "20251013900265",
    "flr_nm": "티에스넥스젠",
    "rcept_dt": "20251013",
    "rm": "코"
  },
  {
    "corp_code": "00317487",
    "corp_name": "티에스넥스젠",
    "stock_code": "043220",
    "corp_cls": "K",
    "report_nm": "불성실공시법인지정예고              (공시번복)",
    "rcept_no": "20251001900878",
    "flr_nm": "코스닥시장본부",
    "rcept_dt": "20251001",
    "rm": "코"
  },
  {
    "corp_code": "00317487",
    "corp_name": "티에스넥스젠",
    "stock_code": "043220",
    "corp_cls": "K",
    "report_nm": "투자판단관련주요경영사항              (담보제공 신탁자산 공매유찰 후 수의계약 체결)",
    "rcept_no": "20251001900316",
    "flr_nm": "티에스넥스젠",
    "rcept_dt": "20251001",
    "rm": "코"
  },
  {
    "corp_code": "00317487",
    "corp_name": "티에스넥스젠",
    "stock_code": "043220",
    "corp_cls": "K",
    "report_nm": "[기재정정]주주총회소집공고",
    "rcept_no": "20250925000243",
    "flr_nm": "티에스넥스젠",
    "rcept_dt": "20250925",
    "rm": ""
  },
  {
    "corp_code": "00317487",
    "corp_name": "티에스넥스젠",
    "stock_code": "043220",
    "corp_cls": "K",
    "report_nm": "[기재정정]주요사항보고서(감자결정)",
    "rcept_no": "20250924000107",
    "flr_nm": "티에스넥스젠",
    "rcept_dt": "20250924",
    "rm": ""
  },
  {
    "corp_code": "00317487",
    "corp_name": "티에스넥스젠",
    "stock_code": "043220",
    "corp_cls": "K",
    "report_nm": "[기재정정]의결권대리행사권유참고서류",
    "rcept_no": "20250924000109",
    "flr_nm": "티에스넥스젠",
    "rcept_dt": "20250924",
    "rm": ""
  },
  {
    "corp_code": "00317487",
    "corp_name": "티에스넥스젠",
    "stock_code": "043220",
    "corp_cls": "K",
    "report_nm": "[기재정정]주주총회소집공고",
    "rcept_no": "20250924000108",
    "flr_nm": "티에스넥스젠",
    "rcept_dt": "20250924",
    "rm": ""
  },
  {
    "corp_code": "00317487",
    "corp_name": "티에스넥스젠",
    "stock_code": "043220",
    "corp_cls": "K",
    "report_nm": "[기재정정]주주총회소집결의              (임시주주총회)",
    "rcept_no": "20250923900181",
    "flr_nm": "티에스넥스젠",
    "rcept_dt": "20250923",
    "rm": "코"
  },
  {
    "corp_code": "00317487",
    "corp_name": "티에스넥스젠",
    "stock_code": "043220",
    "corp_cls": "K",
    "report_nm": "소송등의판결ㆍ결정              (주주명부열람등사 가처분)",
    "rcept_no": "20250923900172",
    "flr_nm": "티에스넥스젠",
    "rcept_dt": "20250923",
    "rm": "코"
  },
  {
    "corp_code": "00317487",
    "corp_name": "티에스넥스젠",
    "stock_code": "043220",
    "corp_cls": "K",
    "report_nm": "의결권대리행사권유참고서류",
    "rcept_no": "20250919000613",
    "flr_nm": "김남수",
    "rcept_dt": "20250919",
    "rm": ""
  },
  {
    "corp_code": "00317487",
    "corp_name": "티에스넥스젠",
    "stock_code": "043220",
    "corp_cls": "K",
    "report_nm": "[기재정정]의결권대리행사권유참고서류",
    "rcept_no": "20250917000201",
    "flr_nm": "티에스넥스젠",
    "rcept_dt": "20250917",
    "rm": "정"
  },
  {
    "corp_code": "00317487",
    "corp_name": "티에스넥스젠",
    "stock_code": "043220",
    "corp_cls": "K",
    "report_nm": "[기재정정]주주총회소집공고",
    "rcept_no": "20250917000200",
    "flr_nm": "티에스넥스젠",
    "rcept_dt": "20250917",
    "rm": "정"
  },
  {
    "corp_code": "00317487",
    "corp_name": "티에스넥스젠",
    "stock_code": "043220",
    "corp_cls": "K",
    "report_nm": "[기재정정]주주총회소집결의              (임시주주총회)",
    "rcept_no": "20250916900222",
    "flr_nm": "티에스넥스젠",
    "rcept_dt": "20250916",
    "rm": "코정"
  },
  {
    "corp_code": "00317487",
    "corp_name": "티에스넥스젠",
    "stock_code": "043220",
    "corp_cls": "K",
    "report_nm": "의결권대리행사권유참고서류",
    "rcept_no": "20250915000316",
    "flr_nm": "티에스넥스젠",
    "rcept_dt": "20250915",
    "rm": "정"
  },
  {
    "corp_code": "00317487",
    "corp_name": "티에스넥스젠",
    "stock_code": "043220",
    "corp_cls": "K",
    "report_nm": "주주총회소집공고",
    "rcept_no": "20250915000314",
    "flr_nm": "티에스넥스젠",
    "rcept_dt": "20250915",
    "rm": "정"
  },
  {
    "corp_code": "00317487",
    "corp_name": "티에스넥스젠",
    "stock_code": "043220",
    "corp_cls": "K",
    "report_nm": "소송등의제기ㆍ신청(경영권분쟁소송)              (주주명부열람등사 가처분)",
    "rcept_no": "20250915900270",
    "flr_nm": "티에스넥스젠",
    "rcept_dt": "20250915",
    "rm": "코"
  },
  {
    "corp_code": "00317487",
    "corp_name": "티에스넥스젠",
    "stock_code": "043220",
    "corp_cls": "K",
    "report_nm": "[기재정정]의결권대리행사권유참고서류",
    "rcept_no": "20250908000219",
    "flr_nm": "김남수",
    "rcept_dt": "20250908",
    "rm": ""
  },
  {
    "corp_code": "00317487",
    "corp_name": "티에스넥스젠",
    "stock_code": "043220",
    "corp_cls": "K",
    "report_nm": "[기재정정]의결권대리행사권유참고서류",
    "rcept_no": "20250905000295",
    "flr_nm": "티에스넥스젠",
    "rcept_dt": "20250905",
    "rm": ""
  },
  {
    "corp_code": "00317487",
    "corp_name": "티에스넥스젠",
    "stock_code": "043220",
    "corp_cls": "K",
    "report_nm": "[기재정정]주주총회소집공고",
    "rcept_no": "20250905000283",
    "flr_nm": "티에스넥스젠",
    "rcept_dt": "20250905",
    "rm": "정"
  },
  {
    "corp_code": "00317487",
    "corp_name": "티에스넥스젠",
    "stock_code": "043220",
    "corp_cls": "K",
    "report_nm": "[기재정정]주요사항보고서(감자결정)",
    "rcept_no": "20250905000233",
    "flr_nm": "티에스넥스젠",
    "rcept_dt": "20250905",
    "rm": "정"
  },
  {
    "corp_code": "00317487",
    "corp_name": "티에스넥스젠",
    "stock_code": "043220",
    "corp_cls": "K",
    "report_nm": "기타주요경영사항              (회사분할결정 철회)",
    "rcept_no": "20250905900238",
    "flr_nm": "티에스넥스젠",
    "rcept_dt": "20250905",
    "rm": "코"
  },
  {
    "corp_code": "00317487",
    "corp_name": "티에스넥스젠",
    "stock_code": "043220",
    "corp_cls": "K",
    "report_nm": "[기재정정]주요사항보고서(회사분할결정)",
    "rcept_no": "20250905000231",
    "flr_nm": "티에스넥스젠",
    "rcept_dt": "20250905",
    "rm": ""
  },
  {
    "corp_code": "00317487",
    "corp_name": "티에스넥스젠",
    "stock_code": "043220",
    "corp_cls": "K",
    "report_nm": "[기재정정]주주총회소집결의              (임시주주총회)",
    "rcept_no": "20250905900203",
    "flr_nm": "티에스넥스젠",
    "rcept_dt": "20250905",
    "rm": "코"
  },
  {
    "corp_code": "00317487",
    "corp_name": "티에스넥스젠",
    "stock_code": "043220",
    "corp_cls": "K",
    "report_nm": "의결권대리행사권유참고서류",
    "rcept_no": "20250828000414",
    "flr_nm": "김남수",
    "rcept_dt": "20250828",
    "rm": "정"
  },
  {
    "corp_code": "00317487",
    "corp_name": "티에스넥스젠",
    "stock_code": "043220",
    "corp_cls": "K",
    "report_nm": "주권매매거래정지기간변경              (감자일정연기)",
    "rcept_no": "20250827900496",
    "flr_nm": "코스닥시장본부",
    "rcept_dt": "20250827",
    "rm": "코"
  },
  {
    "corp_code": "00317487",
    "corp_name": "티에스넥스젠",
    "stock_code": "043220",
    "corp_cls": "K",
    "report_nm": "[기재정정]주요사항보고서(감자결정)",
    "rcept_no": "20250827000561",
    "flr_nm": "티에스넥스젠",
    "rcept_dt": "20250827",
    "rm": "정"
  },
  {
    "corp_code": "00317487",
    "corp_name": "티에스넥스젠",
    "stock_code": "043220",
    "corp_cls": "K",
    "report_nm": "[기재정정]주주총회소집결의              (임시주주총회)",
    "rcept_no": "20250827900403",
    "flr_nm": "티에스넥스젠",
    "rcept_dt": "20250827",
    "rm": "코정"
  },
  {
    "corp_code": "00317487",
    "corp_name": "티에스넥스젠",
    "stock_code": "043220",
    "corp_cls": "K",
    "report_nm": "주주명부폐쇄기간또는기준일설정              ",
    "rcept_no": "20250825900149",
    "flr_nm": "티에스넥스젠",
    "rcept_dt": "20250825",
    "rm": "코"
  },
  {
    "corp_code": "00317487",
    "corp_name": "티에스넥스젠",
    "stock_code": "043220",
    "corp_cls": "K",
    "report_nm": "주주총회소집결의              (임시주주총회)",
    "rcept_no": "20250825900135",
    "flr_nm": "티에스넥스젠",
    "rcept_dt": "20250825",
    "rm": "코정"
  },
  {
    "corp_code": "00317487",
    "corp_name": "티에스넥스젠",
    "stock_code": "043220",
    "corp_cls": "K",
    "report_nm": "주권매매거래정지기간변경              (주식의 병합, 분할 등 전자등록 변경, 말소)",
    "rcept_no": "20250820900414",
    "flr_nm": "코스닥시장본부",
    "rcept_dt": "20250820",
    "rm": "코"
  },
  {
    "corp_code": "00317487",
    "corp_name": "티에스넥스젠",
    "stock_code": "043220",
    "corp_cls": "K",
    "report_nm": "주식등의대량보유상황보고서(일반)",
    "rcept_no": "20250820000115",
    "flr_nm": "시스코바이오투자조합",
    "rcept_dt": "20250820",
    "rm": ""
  },
  {
    "corp_code": "00317487",
    "corp_name": "티에스넥스젠",
    "stock_code": "043220",
    "corp_cls": "K",
    "report_nm": "반기보고서 (2025.06)",
    "rcept_no": "20250814004487",
    "flr_nm": "티에스넥스젠",
    "rcept_dt": "20250814",
    "rm": ""
  },
  {
    "corp_code": "00317487",
    "corp_name": "티에스넥스젠",
    "stock_code": "043220",
    "corp_cls": "K",
    "report_nm": "반기검토(감사)의견부적정등사실확인(자본잠식률100분의50이상또는자기자본10억원미만포함)              ",
    "rcept_no": "20250814903830",
    "flr_nm": "티에스넥스젠",
    "rcept_dt": "20250814",
    "rm": "코"
  },
  {
    "corp_code": "00317487",
    "corp_name": "티에스넥스젠",
    "stock_code": "043220",
    "corp_cls": "K",
    "report_nm": "대출원리금연체사실발생              ",
    "rcept_no": "20250814901276",
    "flr_nm": "티에스넥스젠",
    "rcept_dt": "20250814",
    "rm": "코"
  },
  {
    "corp_code": "00317487",
    "corp_name": "티에스넥스젠",
    "stock_code": "043220",
    "corp_cls": "K",
    "report_nm": "의결권대리행사권유참고서류",
    "rcept_no": "20250812000291",
    "flr_nm": "티에스넥스젠",
    "rcept_dt": "20250812",
    "rm": "정"
  },
  {
    "corp_code": "00317487",
    "corp_name": "티에스넥스젠",
    "stock_code": "043220",
    "corp_cls": "K",
    "report_nm": "주주총회소집공고",
    "rcept_no": "20250812000288",
    "flr_nm": "티에스넥스젠",
    "rcept_dt": "20250812",
    "rm": "정"
  },
  {
    "corp_code": "00317487",
    "corp_name": "티에스넥스젠",
    "stock_code": "043220",
    "corp_cls": "K",
    "report_nm": "주주명부폐쇄기간또는기준일설정              ",
    "rcept_no": "20250808900661",
    "flr_nm": "티에스넥스젠",
    "rcept_dt": "20250808",
    "rm": "코"
  },
  {
    "corp_code": "00317487",
    "corp_name": "티에스넥스젠",
    "stock_code": "043220",
    "corp_cls": "K",
    "report_nm": "주주총회소집결의              (임시주주총회)",
    "rcept_no": "20250808900635",
    "flr_nm": "티에스넥스젠",
    "rcept_dt": "20250808",
    "rm": "코정"
  },
  {
    "corp_code": "00317487",
    "corp_name": "티에스넥스젠",
    "stock_code": "043220",
    "corp_cls": "K",
    "report_nm": "주요사항보고서(감자결정)",
    "rcept_no": "20250808000634",
    "flr_nm": "티에스넥스젠",
    "rcept_dt": "20250811",
    "rm": "정"
  },
  {
    "corp_code": "00317487",
    "corp_name": "티에스넥스젠",
    "stock_code": "043220",
    "corp_cls": "K",
    "report_nm": "주요사항보고서(회사분할결정)",
    "rcept_no": "20250808000637",
    "flr_nm": "티에스넥스젠",
    "rcept_dt": "20250811",
    "rm": "정"
  },
  {
    "corp_code": "00317487",
    "corp_name": "티에스넥스젠",
    "stock_code": "043220",
    "corp_cls": "K",
    "report_nm": "소송등의제기ㆍ신청(경영권분쟁소송)              (임시총회소집허가)",
    "rcept_no": "20250801900547",
    "flr_nm": "티에스넥스젠",
    "rcept_dt": "20250801",
    "rm": "코"
  },
  {
    "corp_code": "00317487",
    "corp_name": "티에스넥스젠",
    "stock_code": "043220",
    "corp_cls": "K",
    "report_nm": "본점소재지변경              ",
    "rcept_no": "20250625900412",
    "flr_nm": "티에스넥스젠",
    "rcept_dt": "20250625",
    "rm": "코"
  },
  {
    "corp_code": "00317487",
    "corp_name": "티에스넥스젠",
    "stock_code": "043220",
    "corp_cls": "K",
    "report_nm": "[기재정정]주요사항보고서(유형자산양도결정)",
    "rcept_no": "20250618000249",
    "flr_nm": "티에스넥스젠",
    "rcept_dt": "20250618",
    "rm": ""
  },
  {
    "corp_code": "00317487",
    "corp_name": "티에스넥스젠",
    "stock_code": "043220",
    "corp_cls": "K",
    "report_nm": "합병등종료보고서(자산양수도)",
    "rcept_no": "20250618000270",
    "flr_nm": "티에스넥스젠",
    "rcept_dt": "20250618",
    "rm": ""
  },
  {
    "corp_code": "00317487",
    "corp_name": "티에스넥스젠",
    "stock_code": "043220",
    "corp_cls": "K",
    "report_nm": "주요사항보고서(유형자산양도결정)",
    "rcept_no": "20250610000217",
    "flr_nm": "티에스넥스젠",
    "rcept_dt": "20250610",
    "rm": "정"
  },
  {
    "corp_code": "00317487",
    "corp_name": "티에스넥스젠",
    "stock_code": "043220",
    "corp_cls": "K",
    "report_nm": "전환가액의조정              (제11회차)",
    "rcept_no": "20250604900107",
    "flr_nm": "티에스넥스젠",
    "rcept_dt": "20250604",
    "rm": "코"
  },
  {
    "corp_code": "00317487",
    "corp_name": "티에스넥스젠",
    "stock_code": "043220",
    "corp_cls": "K",
    "report_nm": "분기보고서 (2025.03)",
    "rcept_no": "20250515001227",
    "flr_nm": "티에스넥스젠",
    "rcept_dt": "20250515",
    "rm": ""
  },
  {
    "corp_code": "00317487",
    "corp_name": "티에스넥스젠",
    "stock_code": "043220",
    "corp_cls": "K",
    "report_nm": "임시주주총회결과              ",
    "rcept_no": "20250430900514",
    "flr_nm": "티에스넥스젠",
    "rcept_dt": "20250430",
    "rm": "코"
  },
  {
    "corp_code": "00317487",
    "corp_name": "티에스넥스젠",
    "stock_code": "043220",
    "corp_cls": "K",
    "report_nm": "대출원리금연체사실발생              ",
    "rcept_no": "20250422900001",
    "flr_nm": "티에스넥스젠",
    "rcept_dt": "20250422",
    "rm": "코"
  },
  {
    "corp_code": "00317487",
    "corp_name": "티에스넥스젠",
    "stock_code": "043220",
    "corp_cls": "K",
    "report_nm": "주권매매거래정지기간변경              (개선기간 부여)",
    "rcept_no": "20250421900791",
    "flr_nm": "코스닥시장본부",
    "rcept_dt": "20250421",
    "rm": "코"
  },
  {
    "corp_code": "00317487",
    "corp_name": "티에스넥스젠",
    "stock_code": "043220",
    "corp_cls": "K",
    "report_nm": "기타시장안내              (상장폐지 관련 이의신청서 접수 및 개선기간 부여)",
    "rcept_no": "20250421900790",
    "flr_nm": "코스닥시장본부",
    "rcept_dt": "20250421",
    "rm": "코"
  },
  {
    "corp_code": "00317487",
    "corp_name": "티에스넥스젠",
    "stock_code": "043220",
    "corp_cls": "K",
    "report_nm": "사채원리금미지급발생              ",
    "rcept_no": "20250421900001",
    "flr_nm": "티에스넥스젠",
    "rcept_dt": "20250421",
    "rm": "코"
  },
  {
    "corp_code": "00317487",
    "corp_name": "티에스넥스젠",
    "stock_code": "043220",
    "corp_cls": "K",
    "report_nm": "기타주요경영사항              (조회공시요구(현저한 시황변동)에 대한 답변)",
    "rcept_no": "20250416900349",
    "flr_nm": "티에스넥스젠",
    "rcept_dt": "20250416",
    "rm": "코"
  },
  {
    "corp_code": "00317487",
    "corp_name": "티에스넥스젠",
    "stock_code": "043220",
    "corp_cls": "K",
    "report_nm": "의결권대리행사권유참고서류",
    "rcept_no": "20250415000324",
    "flr_nm": "티에스넥스젠",
    "rcept_dt": "20250415",
    "rm": ""
  },
  {
    "corp_code": "00317487",
    "corp_name": "티에스넥스젠",
    "stock_code": "043220",
    "corp_cls": "K",
    "report_nm": "주주총회소집공고",
    "rcept_no": "20250415000314",
    "flr_nm": "티에스넥스젠",
    "rcept_dt": "20250415",
    "rm": ""
  },
  {
    "corp_code": "00317487",
    "corp_name": "티에스넥스젠",
    "stock_code": "043220",
    "corp_cls": "K",
    "report_nm": "[기재정정]주주총회소집결의              (임시주주총회)",
    "rcept_no": "20250415900332",
    "flr_nm": "티에스넥스젠",
    "rcept_dt": "20250415",
    "rm": "코"
  },
  {
    "corp_code": "00317487",
    "corp_name": "티에스넥스젠",
    "stock_code": "043220",
    "corp_cls": "K",
    "report_nm": "신주인수권행사가액의조정              (제16회차)",
    "rcept_no": "20250414900412",
    "flr_nm": "티에스넥스젠",
    "rcept_dt": "20250414",
    "rm": "코"
  },
  {
    "corp_code": "00317487",
    "corp_name": "티에스넥스젠",
    "stock_code": "043220",
    "corp_cls": "K",
    "report_nm": "주식등의대량보유상황보고서(약식)",
    "rcept_no": "20250410002925",
    "flr_nm": "상상인저축은행",
    "rcept_dt": "20250410",
    "rm": ""
  },
  {
    "corp_code": "00317487",
    "corp_name": "티에스넥스젠",
    "stock_code": "043220",
    "corp_cls": "K",
    "report_nm": "대표이사변경              ",
    "rcept_no": "20250410900548",
    "flr_nm": "티에스넥스젠",
    "rcept_dt": "20250410",
    "rm": "코"
  },
  {
    "corp_code": "00317487",
    "corp_name": "티에스넥스젠",
    "stock_code": "043220",
    "corp_cls": "K",
    "report_nm": "불성실공시법인지정              (공시번복 3건)",
    "rcept_no": "20250408901029",
    "flr_nm": "코스닥시장본부",
    "rcept_dt": "20250408",
    "rm": "코"
  },
  {
    "corp_code": "00317487",
    "corp_name": "티에스넥스젠",
    "stock_code": "043220",
    "corp_cls": "K",
    "report_nm": "[기재정정]정기주주총회결과              (연회)",
    "rcept_no": "20250408900500",
    "flr_nm": "티에스넥스젠",
    "rcept_dt": "20250408",
    "rm": "코"
  },
  {
    "corp_code": "00317487",
    "corp_name": "티에스넥스젠",
    "stock_code": "043220",
    "corp_cls": "K",
    "report_nm": "[기재정정]정기주주총회결과              (연회)",
    "rcept_no": "20250407900463",
    "flr_nm": "티에스넥스젠",
    "rcept_dt": "20250407",
    "rm": "코정"
  },
  {
    "corp_code": "00317487",
    "corp_name": "티에스넥스젠",
    "stock_code": "043220",
    "corp_cls": "K",
    "report_nm": "대표이사변경              ",
    "rcept_no": "20250401901070",
    "flr_nm": "티에스넥스젠",
    "rcept_dt": "20250401",
    "rm": "코"
  },
  {
    "corp_code": "00317487",
    "corp_name": "티에스넥스젠",
    "stock_code": "043220",
    "corp_cls": "K",
    "report_nm": "주권매매거래정지기간변경              (상장폐지 사유 발생)",
    "rcept_no": "20250331904042",
    "flr_nm": "코스닥시장본부",
    "rcept_dt": "20250331",
    "rm": "코"
  },
  {
    "corp_code": "00317487",
    "corp_name": "티에스넥스젠",
    "stock_code": "043220",
    "corp_cls": "K",
    "report_nm": "기타시장안내              (상장폐지 관련)",
    "rcept_no": "20250331904031",
    "flr_nm": "코스닥시장본부",
    "rcept_dt": "20250331",
    "rm": "코"
  },
  {
    "corp_code": "00317487",
    "corp_name": "티에스넥스젠",
    "stock_code": "043220",
    "corp_cls": "K",
    "report_nm": "정기주주총회결과              ",
    "rcept_no": "20250331903966",
    "flr_nm": "티에스넥스젠",
    "rcept_dt": "20250331",
    "rm": "코정"
  },
  {
    "corp_code": "00317487",
    "corp_name": "티에스넥스젠",
    "stock_code": "043220",
    "corp_cls": "K",
    "report_nm": "사외이사의선임ㆍ해임또는중도퇴임에관한신고",
    "rcept_no": "20250331004337",
    "flr_nm": "티에스넥스젠",
    "rcept_dt": "20250331",
    "rm": ""
  },
  {
    "corp_code": "00317487",
    "corp_name": "티에스넥스젠",
    "stock_code": "043220",
    "corp_cls": "K",
    "report_nm": "감사보고서제출              ",
    "rcept_no": "20250331903476",
    "flr_nm": "티에스넥스젠",
    "rcept_dt": "20250331",
    "rm": "코"
  },
  {
    "corp_code": "00317487",
    "corp_name": "티에스넥스젠",
    "stock_code": "043220",
    "corp_cls": "K",
    "report_nm": "사업보고서 (2024.12)",
    "rcept_no": "20250331003863",
    "flr_nm": "티에스넥스젠",
    "rcept_dt": "20250331",
    "rm": "연"
  },
  {
    "corp_code": "00317487",
    "corp_name": "티에스넥스젠",
    "stock_code": "043220",
    "corp_cls": "K",
    "report_nm": "단기차입금증가결정              ",
    "rcept_no": "20250331902533",
    "flr_nm": "티에스넥스젠",
    "rcept_dt": "20250331",
    "rm": "코"
  },
  {
    "corp_code": "00317487",
    "corp_name": "티에스넥스젠",
    "stock_code": "043220",
    "corp_cls": "K",
    "report_nm": "조회공시요구(풍문또는보도)              (감사의견 비적정설)",
    "rcept_no": "20250331902247",
    "flr_nm": "코스닥시장본부",
    "rcept_dt": "20250331",
    "rm": "코"
  },
  {
    "corp_code": "00317487",
    "corp_name": "티에스넥스젠",
    "stock_code": "043220",
    "corp_cls": "K",
    "report_nm": "주권매매거래정지              (풍문 또는 보도 관련)",
    "rcept_no": "20250331902245",
    "flr_nm": "코스닥시장본부",
    "rcept_dt": "20250331",
    "rm": "코"
  },
  {
    "corp_code": "00317487",
    "corp_name": "티에스넥스젠",
    "stock_code": "043220",
    "corp_cls": "K",
    "report_nm": "전환사채(해외전환사채포함)발행후만기전사채취득              ",
    "rcept_no": "20250331901849",
    "flr_nm": "티에스넥스젠",
    "rcept_dt": "20250331",
    "rm": "코"
  },
  {
    "corp_code": "00317487",
    "corp_name": "티에스넥스젠",
    "stock_code": "043220",
    "corp_cls": "K",
    "report_nm": "[기재정정]주주총회소집결의              (임시주주총회)",
    "rcept_no": "20250328902543",
    "flr_nm": "티에스넥스젠",
    "rcept_dt": "20250328",
    "rm": "코정"
  },
  {
    "corp_code": "00317487",
    "corp_name": "티에스넥스젠",
    "stock_code": "043220",
    "corp_cls": "K",
    "report_nm": "[기재정정]사업보고서제출기한연장신고서 (2024.12)",
    "rcept_no": "20250321001981",
    "flr_nm": "티에스넥스젠",
    "rcept_dt": "20250321",
    "rm": ""
  },
  {
    "corp_code": "00317487",
    "corp_name": "티에스넥스젠",
    "stock_code": "043220",
    "corp_cls": "K",
    "report_nm": "사업보고서제출기한연장신고서 (2024.12)",
    "rcept_no": "20250321001973",
    "flr_nm": "티에스넥스젠",
    "rcept_dt": "20250321",
    "rm": "정"
  },
  {
    "corp_code": "00317487",
    "corp_name": "티에스넥스젠",
    "stock_code": "043220",
    "corp_cls": "K",
    "report_nm": "기타경영사항(자율공시)              (감사보고서 제출 지연)",
    "rcept_no": "20250321901647",
    "flr_nm": "티에스넥스젠",
    "rcept_dt": "20250321",
    "rm": "코"
  },
  {
    "corp_code": "00317487",
    "corp_name": "티에스넥스젠",
    "stock_code": "043220",
    "corp_cls": "K",
    "report_nm": "[기재정정]단일판매ㆍ공급계약체결              ",
    "rcept_no": "20250321901095",
    "flr_nm": "티에스넥스젠",
    "rcept_dt": "20250321",
    "rm": "코"
  },
  {
    "corp_code": "00317487",
    "corp_name": "티에스넥스젠",
    "stock_code": "043220",
    "corp_cls": "K",
    "report_nm": "조회공시요구(현저한시황변동)에대한답변(미확정)              ",
    "rcept_no": "20250317900902",
    "flr_nm": "티에스넥스젠",
    "rcept_dt": "20250317",
    "rm": "코"
  },
  {
    "corp_code": "00317487",
    "corp_name": "티에스넥스젠",
    "stock_code": "043220",
    "corp_cls": "K",
    "report_nm": "불성실공시법인지정예고              (공시번복 3건)",
    "rcept_no": "20250314902317",
    "flr_nm": "코스닥시장본부",
    "rcept_dt": "20250314",
    "rm": "코"
  },
  {
    "corp_code": "00317487",
    "corp_name": "티에스넥스젠",
    "stock_code": "043220",
    "corp_cls": "K",
    "report_nm": "의결권대리행사권유참고서류",
    "rcept_no": "20250314001509",
    "flr_nm": "티에스넥스젠",
    "rcept_dt": "20250314",
    "rm": ""
  },
  {
    "corp_code": "00317487",
    "corp_name": "티에스넥스젠",
    "stock_code": "043220",
    "corp_cls": "K",
    "report_nm": "주주총회소집공고",
    "rcept_no": "20250314001447",
    "flr_nm": "티에스넥스젠",
    "rcept_dt": "20250314",
    "rm": ""
  },
  {
    "corp_code": "00317487",
    "corp_name": "티에스넥스젠",
    "stock_code": "043220",
    "corp_cls": "K",
    "report_nm": "주주총회소집결의              ",
    "rcept_no": "20250314901560",
    "flr_nm": "티에스넥스젠",
    "rcept_dt": "20250314",
    "rm": "코"
  },
  {
    "corp_code": "00317487",
    "corp_name": "티에스넥스젠",
    "stock_code": "043220",
    "corp_cls": "K",
    "report_nm": "[기재정정]매출액또는손익구조30%(대규모법인은15%)이상변동              ",
    "rcept_no": "20250314901336",
    "flr_nm": "티에스넥스젠",
    "rcept_dt": "20250314",
    "rm": "코"
  },
  {
    "corp_code": "00317487",
    "corp_name": "티에스넥스젠",
    "stock_code": "043220",
    "corp_cls": "K",
    "report_nm": "전환사채(해외전환사채포함)발행후만기전사채취득              ",
    "rcept_no": "20250307901009",
    "flr_nm": "티에스넥스젠",
    "rcept_dt": "20250307",
    "rm": "코"
  },
  {
    "corp_code": "00317487",
    "corp_name": "티에스넥스젠",
    "stock_code": "043220",
    "corp_cls": "K",
    "report_nm": "매출액또는손익구조30%(대규모법인은15%)이상변동              ",
    "rcept_no": "20250228901662",
    "flr_nm": "티에스넥스젠",
    "rcept_dt": "20250228",
    "rm": "코정"
  },
  {
    "corp_code": "00317487",
    "corp_name": "티에스넥스젠",
    "stock_code": "043220",
    "corp_cls": "K",
    "report_nm": "[기재정정]주주총회소집결의              (임시주주총회)",
    "rcept_no": "20250225900844",
    "flr_nm": "티에스넥스젠",
    "rcept_dt": "20250225",
    "rm": "코정"
  },
  {
    "corp_code": "00317487",
    "corp_name": "티에스넥스젠",
    "stock_code": "043220",
    "corp_cls": "K",
    "report_nm": "조회공시요구(현저한시황변동)에대한답변(미확정)              ",
    "rcept_no": "20250218900335",
    "flr_nm": "티에스넥스젠",
    "rcept_dt": "20250218",
    "rm": "코"
  },
  {
    "corp_code": "00317487",
    "corp_name": "티에스넥스젠",
    "stock_code": "043220",
    "corp_cls": "K",
    "report_nm": "조회공시요구(현저한시황변동)              ",
    "rcept_no": "20250217901069",
    "flr_nm": "코스닥시장본부",
    "rcept_dt": "20250217",
    "rm": "코"
  },
  {
    "corp_code": "00317487",
    "corp_name": "티에스넥스젠",
    "stock_code": "043220",
    "corp_cls": "K",
    "report_nm": "[기재정정]주주총회소집결의              (임시주주총회)",
    "rcept_no": "20250217900619",
    "flr_nm": "티에스넥스젠",
    "rcept_dt": "20250217",
    "rm": "코정"
  },
  {
    "corp_code": "00317487",
    "corp_name": "티에스넥스젠",
    "stock_code": "043220",
    "corp_cls": "K",
    "report_nm": "기타주요경영사항              (제13, 14, 15회차 무기명식 이권부 무보증 비분리형 사모 신주인수권부사채 발행 결정 철회)",
    "rcept_no": "20250213900797",
    "flr_nm": "코스닥시장본부",
    "rcept_dt": "20250213",
    "rm": "코"
  },
  {
    "corp_code": "00317487",
    "corp_name": "티에스넥스젠",
    "stock_code": "043220",
    "corp_cls": "K",
    "report_nm": "[기재정정]주요사항보고서(신주인수권부사채권발행결정)",
    "rcept_no": "20250213001298",
    "flr_nm": "티에스넥스젠",
    "rcept_dt": "20250213",
    "rm": ""
  },
  {
    "corp_code": "00317487",
    "corp_name": "티에스넥스젠",
    "stock_code": "043220",
    "corp_cls": "K",
    "report_nm": "[기재정정]주요사항보고서(신주인수권부사채권발행결정)",
    "rcept_no": "20250213001281",
    "flr_nm": "티에스넥스젠",
    "rcept_dt": "20250213",
    "rm": ""
  },
  {
    "corp_code": "00317487",
    "corp_name": "티에스넥스젠",
    "stock_code": "043220",
    "corp_cls": "K",
    "report_nm": "[기재정정]주요사항보고서(신주인수권부사채권발행결정)",
    "rcept_no": "20250213001252",
    "flr_nm": "티에스넥스젠",
    "rcept_dt": "20250213",
    "rm": ""
  },
  {
    "corp_code": "00317487",
    "corp_name": "티에스넥스젠",
    "stock_code": "043220",
    "corp_cls": "K",
    "report_nm": "주주총회소집결의              ",
    "rcept_no": "20250116900386",
    "flr_nm": "티에스넥스젠",
    "rcept_dt": "20250116",
    "rm": "코정"
  },
  {
    "corp_code": "00317487",
    "corp_name": "티에스넥스젠",
    "stock_code": "043220",
    "corp_cls": "K",
    "report_nm": "주주명부폐쇄기간또는기준일설정              ",
    "rcept_no": "20250116900344",
    "flr_nm": "티에스넥스젠",
    "rcept_dt": "20250116",
    "rm": "코"
  }
]