[
  {
    "corp_code": "01318933",
    "corp_name": "지니틱스",
    "stock_code": "303030",
    "corp_cls": "K",
    "report_nm": "분기보고서 (2026.03)",
    "rcept_no": "20260515001417",
    "flr_nm": "지니틱스",
    "rcept_dt": "20260515",
    "rm": ""
  },
  {
    "corp_code": "01318933",
    "corp_name": "지니틱스",
    "stock_code": "303030",
    "corp_cls": "K",
    "report_nm": "주권매매거래정지해제              (액면병합 주권 변경상장)",
    "rcept_no": "20260506901022",
    "flr_nm": "코스닥시장본부",
    "rcept_dt": "20260506",
    "rm": "코"
  },
  {
    "corp_code": "01318933",
    "corp_name": "지니틱스",
    "stock_code": "303030",
    "corp_cls": "K",
    "report_nm": "주권매매거래정지              (주식의 병합, 분할 등 전자등록 변경, 말소)",
    "rcept_no": "20260409901103",
    "flr_nm": "코스닥시장본부",
    "rcept_dt": "20260409",
    "rm": "코"
  },
  {
    "corp_code": "01318933",
    "corp_name": "지니틱스",
    "stock_code": "303030",
    "corp_cls": "K",
    "report_nm": "[기재정정]주요사항보고서(유상증자결정)",
    "rcept_no": "20260408000001",
    "flr_nm": "지니틱스",
    "rcept_dt": "20260408",
    "rm": ""
  },
  {
    "corp_code": "01318933",
    "corp_name": "지니틱스",
    "stock_code": "303030",
    "corp_cls": "K",
    "report_nm": "임원ㆍ주요주주특정증권등소유상황보고서",
    "rcept_no": "20260403003155",
    "flr_nm": "헤일로마이크로일렉트로닉스인터내셔널코퍼레이션",
    "rcept_dt": "20260403",
    "rm": ""
  },
  {
    "corp_code": "01318933",
    "corp_name": "지니틱스",
    "stock_code": "303030",
    "corp_cls": "K",
    "report_nm": "주식등의대량보유상황보고서(일반)",
    "rcept_no": "20260403003077",
    "flr_nm": "헤일로마이크로일렉트로닉스인터내셔널코퍼레이션",
    "rcept_dt": "20260403",
    "rm": ""
  },
  {
    "corp_code": "01318933",
    "corp_name": "지니틱스",
    "stock_code": "303030",
    "corp_cls": "K",
    "report_nm": "[기재정정]주식병합결정              ",
    "rcept_no": "20260331900571",
    "flr_nm": "지니틱스",
    "rcept_dt": "20260331",
    "rm": "코"
  },
  {
    "corp_code": "01318933",
    "corp_name": "지니틱스",
    "stock_code": "303030",
    "corp_cls": "K",
    "report_nm": "증권발행결과(자율공시)              ",
    "rcept_no": "20260327901032",
    "flr_nm": "지니틱스",
    "rcept_dt": "20260327",
    "rm": "코"
  },
  {
    "corp_code": "01318933",
    "corp_name": "지니틱스",
    "stock_code": "303030",
    "corp_cls": "K",
    "report_nm": "주식매수선택권부여에관한신고",
    "rcept_no": "20260326000893",
    "flr_nm": "지니틱스",
    "rcept_dt": "20260326",
    "rm": ""
  },
  {
    "corp_code": "01318933",
    "corp_name": "지니틱스",
    "stock_code": "303030",
    "corp_cls": "K",
    "report_nm": "[기재정정]주식매수선택권부여에관한신고",
    "rcept_no": "20260326000764",
    "flr_nm": "지니틱스",
    "rcept_dt": "20260326",
    "rm": ""
  },
  {
    "corp_code": "01318933",
    "corp_name": "지니틱스",
    "stock_code": "303030",
    "corp_cls": "K",
    "report_nm": "정기주주총회결과              ",
    "rcept_no": "20260326900544",
    "flr_nm": "지니틱스",
    "rcept_dt": "20260326",
    "rm": "코"
  },
  {
    "corp_code": "01318933",
    "corp_name": "지니틱스",
    "stock_code": "303030",
    "corp_cls": "K",
    "report_nm": "[기재정정]사업보고서 (2025.12)",
    "rcept_no": "20260325000837",
    "flr_nm": "지니틱스",
    "rcept_dt": "20260325",
    "rm": ""
  },
  {
    "corp_code": "01318933",
    "corp_name": "지니틱스",
    "stock_code": "303030",
    "corp_cls": "K",
    "report_nm": "사업보고서 (2025.12)",
    "rcept_no": "20260318001048",
    "flr_nm": "지니틱스",
    "rcept_dt": "20260318",
    "rm": "정"
  },
  {
    "corp_code": "01318933",
    "corp_name": "지니틱스",
    "stock_code": "303030",
    "corp_cls": "K",
    "report_nm": "주요사항보고서(유상증자결정)",
    "rcept_no": "20260318000539",
    "flr_nm": "지니틱스",
    "rcept_dt": "20260318",
    "rm": "정"
  },
  {
    "corp_code": "01318933",
    "corp_name": "지니틱스",
    "stock_code": "303030",
    "corp_cls": "K",
    "report_nm": "감사보고서제출              ",
    "rcept_no": "20260318900144",
    "flr_nm": "지니틱스",
    "rcept_dt": "20260318",
    "rm": "코"
  },
  {
    "corp_code": "01318933",
    "corp_name": "지니틱스",
    "stock_code": "303030",
    "corp_cls": "K",
    "report_nm": "주주총회소집공고",
    "rcept_no": "20260310002646",
    "flr_nm": "지니틱스",
    "rcept_dt": "20260310",
    "rm": ""
  },
  {
    "corp_code": "01318933",
    "corp_name": "지니틱스",
    "stock_code": "303030",
    "corp_cls": "K",
    "report_nm": "주주총회소집결의              ",
    "rcept_no": "20260310900979",
    "flr_nm": "지니틱스",
    "rcept_dt": "20260310",
    "rm": "코"
  },
  {
    "corp_code": "01318933",
    "corp_name": "지니틱스",
    "stock_code": "303030",
    "corp_cls": "K",
    "report_nm": "주식병합결정              ",
    "rcept_no": "20260310900977",
    "flr_nm": "지니틱스",
    "rcept_dt": "20260310",
    "rm": "코정"
  },
  {
    "corp_code": "01318933",
    "corp_name": "지니틱스",
    "stock_code": "303030",
    "corp_cls": "K",
    "report_nm": "임시주주총회결과              ",
    "rcept_no": "20260226900225",
    "flr_nm": "지니틱스",
    "rcept_dt": "20260226",
    "rm": "코"
  },
  {
    "corp_code": "01318933",
    "corp_name": "지니틱스",
    "stock_code": "303030",
    "corp_cls": "K",
    "report_nm": "주주총회소집공고",
    "rcept_no": "20260211000616",
    "flr_nm": "지니틱스",
    "rcept_dt": "20260211",
    "rm": ""
  },
  {
    "corp_code": "01318933",
    "corp_name": "지니틱스",
    "stock_code": "303030",
    "corp_cls": "K",
    "report_nm": "매출액또는손익구조30%(대규모법인은15%)이상변동              ",
    "rcept_no": "20260129900898",
    "flr_nm": "지니틱스",
    "rcept_dt": "20260129",
    "rm": "코"
  },
  {
    "corp_code": "01318933",
    "corp_name": "지니틱스",
    "stock_code": "303030",
    "corp_cls": "K",
    "report_nm": "주주명부폐쇄기간또는기준일설정              ",
    "rcept_no": "20260119900614",
    "flr_nm": "지니틱스",
    "rcept_dt": "20260119",
    "rm": "코"
  },
  {
    "corp_code": "01318933",
    "corp_name": "지니틱스",
    "stock_code": "303030",
    "corp_cls": "K",
    "report_nm": "[기재정정]주주총회소집결의              (임시주주총회)",
    "rcept_no": "20260119900577",
    "flr_nm": "지니틱스",
    "rcept_dt": "20260119",
    "rm": "코"
  },
  {
    "corp_code": "01318933",
    "corp_name": "지니틱스",
    "stock_code": "303030",
    "corp_cls": "K",
    "report_nm": "주주명부폐쇄기간또는기준일설정              ",
    "rcept_no": "20251212900634",
    "flr_nm": "지니틱스",
    "rcept_dt": "20251212",
    "rm": "코"
  },
  {
    "corp_code": "01318933",
    "corp_name": "지니틱스",
    "stock_code": "303030",
    "corp_cls": "K",
    "report_nm": "분기보고서 (2025.09)",
    "rcept_no": "20251114001110",
    "flr_nm": "지니틱스",
    "rcept_dt": "20251114",
    "rm": ""
  },
  {
    "corp_code": "01318933",
    "corp_name": "지니틱스",
    "stock_code": "303030",
    "corp_cls": "K",
    "report_nm": "임시주주총회결과              ",
    "rcept_no": "20251107900121",
    "flr_nm": "지니틱스",
    "rcept_dt": "20251107",
    "rm": "코"
  },
  {
    "corp_code": "01318933",
    "corp_name": "지니틱스",
    "stock_code": "303030",
    "corp_cls": "K",
    "report_nm": "주주총회소집공고",
    "rcept_no": "20251022000153",
    "flr_nm": "지니틱스",
    "rcept_dt": "20251022",
    "rm": ""
  },
  {
    "corp_code": "01318933",
    "corp_name": "지니틱스",
    "stock_code": "303030",
    "corp_cls": "K",
    "report_nm": "[기재정정]주식매수선택권부여에관한신고",
    "rcept_no": "20251022000149",
    "flr_nm": "지니틱스",
    "rcept_dt": "20251022",
    "rm": ""
  },
  {
    "corp_code": "01318933",
    "corp_name": "지니틱스",
    "stock_code": "303030",
    "corp_cls": "K",
    "report_nm": "[기재정정]주주총회소집결의              (임시주주총회)",
    "rcept_no": "20251022900225",
    "flr_nm": "지니틱스",
    "rcept_dt": "20251022",
    "rm": "코"
  },
  {
    "corp_code": "01318933",
    "corp_name": "지니틱스",
    "stock_code": "303030",
    "corp_cls": "K",
    "report_nm": "소송등의판결ㆍ결정              (경영권 분쟁 소송)(이사해임청구)",
    "rcept_no": "20251015900427",
    "flr_nm": "지니틱스",
    "rcept_dt": "20251015",
    "rm": "코"
  },
  {
    "corp_code": "01318933",
    "corp_name": "지니틱스",
    "stock_code": "303030",
    "corp_cls": "K",
    "report_nm": "소송등의판결ㆍ결정              (직무집행정지 및 직무대행자 선임-소취하)",
    "rcept_no": "20251014900340",
    "flr_nm": "지니틱스",
    "rcept_dt": "20251014",
    "rm": "코"
  },
  {
    "corp_code": "01318933",
    "corp_name": "지니틱스",
    "stock_code": "303030",
    "corp_cls": "K",
    "report_nm": "소송등의판결ㆍ결정              (임시주주총회 소집허가 신청서-소취하)",
    "rcept_no": "20251014900337",
    "flr_nm": "지니틱스",
    "rcept_dt": "20251014",
    "rm": "코"
  },
  {
    "corp_code": "01318933",
    "corp_name": "지니틱스",
    "stock_code": "303030",
    "corp_cls": "K",
    "report_nm": "임원ㆍ주요주주특정증권등소유상황보고서",
    "rcept_no": "20251014000069",
    "flr_nm": "헤일로전자",
    "rcept_dt": "20251014",
    "rm": ""
  },
  {
    "corp_code": "01318933",
    "corp_name": "지니틱스",
    "stock_code": "303030",
    "corp_cls": "K",
    "report_nm": "임원ㆍ주요주주특정증권등소유상황보고서",
    "rcept_no": "20251014000055",
    "flr_nm": "헤일로마이크로일렉트로닉스(홍콩)",
    "rcept_dt": "20251014",
    "rm": ""
  },
  {
    "corp_code": "01318933",
    "corp_name": "지니틱스",
    "stock_code": "303030",
    "corp_cls": "K",
    "report_nm": "소송등의판결ㆍ결정              (장부등열람허용가처분-소취하)",
    "rcept_no": "20251013900184",
    "flr_nm": "지니틱스",
    "rcept_dt": "20251013",
    "rm": "코"
  },
  {
    "corp_code": "01318933",
    "corp_name": "지니틱스",
    "stock_code": "303030",
    "corp_cls": "K",
    "report_nm": "사외이사의선임ㆍ해임또는중도퇴임에관한신고",
    "rcept_no": "20250929000478",
    "flr_nm": "지니틱스",
    "rcept_dt": "20250929",
    "rm": ""
  },
  {
    "corp_code": "01318933",
    "corp_name": "지니틱스",
    "stock_code": "303030",
    "corp_cls": "K",
    "report_nm": "대표이사변경              ",
    "rcept_no": "20250929900541",
    "flr_nm": "지니틱스",
    "rcept_dt": "20250929",
    "rm": "코"
  },
  {
    "corp_code": "01318933",
    "corp_name": "지니틱스",
    "stock_code": "303030",
    "corp_cls": "K",
    "report_nm": "임시주주총회결과              ",
    "rcept_no": "20250929900522",
    "flr_nm": "지니틱스",
    "rcept_dt": "20250929",
    "rm": "코"
  },
  {
    "corp_code": "01318933",
    "corp_name": "지니틱스",
    "stock_code": "303030",
    "corp_cls": "K",
    "report_nm": "소송등의제기ㆍ신청(경영권분쟁소송)              (장부등열람허용가처분)",
    "rcept_no": "20250922900308",
    "flr_nm": "지니틱스",
    "rcept_dt": "20250922",
    "rm": "코"
  },
  {
    "corp_code": "01318933",
    "corp_name": "지니틱스",
    "stock_code": "303030",
    "corp_cls": "K",
    "report_nm": "주주명부폐쇄기간또는기준일설정              ",
    "rcept_no": "20250916900436",
    "flr_nm": "지니틱스",
    "rcept_dt": "20250916",
    "rm": "코"
  },
  {
    "corp_code": "01318933",
    "corp_name": "지니틱스",
    "stock_code": "303030",
    "corp_cls": "K",
    "report_nm": "주주총회소집결의              (임시주주총회)",
    "rcept_no": "20250916900399",
    "flr_nm": "지니틱스",
    "rcept_dt": "20250916",
    "rm": "코정"
  },
  {
    "corp_code": "01318933",
    "corp_name": "지니틱스",
    "stock_code": "303030",
    "corp_cls": "K",
    "report_nm": "소송등의판결ㆍ결정              (경영권 분쟁 소송)(장부등열람허용가처분)",
    "rcept_no": "20250915900217",
    "flr_nm": "지니틱스",
    "rcept_dt": "20250915",
    "rm": "코"
  },
  {
    "corp_code": "01318933",
    "corp_name": "지니틱스",
    "stock_code": "303030",
    "corp_cls": "K",
    "report_nm": "소송등의판결ㆍ결정              (경영권 분쟁 소송)(증거보전)",
    "rcept_no": "20250911900450",
    "flr_nm": "지니틱스",
    "rcept_dt": "20250911",
    "rm": "코"
  },
  {
    "corp_code": "01318933",
    "corp_name": "지니틱스",
    "stock_code": "303030",
    "corp_cls": "K",
    "report_nm": "의결권대리행사권유참고서류",
    "rcept_no": "20250910000607",
    "flr_nm": "헤일로전자",
    "rcept_dt": "20250910",
    "rm": ""
  },
  {
    "corp_code": "01318933",
    "corp_name": "지니틱스",
    "stock_code": "303030",
    "corp_cls": "K",
    "report_nm": "주주총회소집공고",
    "rcept_no": "20250910000590",
    "flr_nm": "지니틱스",
    "rcept_dt": "20250910",
    "rm": ""
  },
  {
    "corp_code": "01318933",
    "corp_name": "지니틱스",
    "stock_code": "303030",
    "corp_cls": "K",
    "report_nm": "[기재정정]주주총회소집결의              (임시주주총회)",
    "rcept_no": "20250909900302",
    "flr_nm": "지니틱스",
    "rcept_dt": "20250909",
    "rm": "코"
  },
  {
    "corp_code": "01318933",
    "corp_name": "지니틱스",
    "stock_code": "303030",
    "corp_cls": "K",
    "report_nm": "[기재정정]주주총회소집결의              (임시주주총회)",
    "rcept_no": "20250909900222",
    "flr_nm": "지니틱스",
    "rcept_dt": "20250909",
    "rm": "코정"
  },
  {
    "corp_code": "01318933",
    "corp_name": "지니틱스",
    "stock_code": "303030",
    "corp_cls": "K",
    "report_nm": "소송등의제기ㆍ신청(경영권분쟁소송)              (장부등열람허용가처분)",
    "rcept_no": "20250908900300",
    "flr_nm": "지니틱스",
    "rcept_dt": "20250908",
    "rm": "코"
  },
  {
    "corp_code": "01318933",
    "corp_name": "지니틱스",
    "stock_code": "303030",
    "corp_cls": "K",
    "report_nm": "[기재정정]주주총회소집결의              (임시주주총회)",
    "rcept_no": "20250903900452",
    "flr_nm": "지니틱스",
    "rcept_dt": "20250903",
    "rm": "코정"
  },
  {
    "corp_code": "01318933",
    "corp_name": "지니틱스",
    "stock_code": "303030",
    "corp_cls": "K",
    "report_nm": "소송등의판결ㆍ결정              (경영권 분쟁 소송)(장부등열람허용가처분)",
    "rcept_no": "20250903900212",
    "flr_nm": "지니틱스",
    "rcept_dt": "20250903",
    "rm": "코"
  },
  {
    "corp_code": "01318933",
    "corp_name": "지니틱스",
    "stock_code": "303030",
    "corp_cls": "K",
    "report_nm": "소송등의판결ㆍ결정              (경영권 분쟁 소송)(주주총회 개최금지 가처분)",
    "rcept_no": "20250903900210",
    "flr_nm": "지니틱스",
    "rcept_dt": "20250903",
    "rm": "코"
  },
  {
    "corp_code": "01318933",
    "corp_name": "지니틱스",
    "stock_code": "303030",
    "corp_cls": "K",
    "report_nm": "소송등의제기ㆍ신청(경영권분쟁소송)              (임시주주총회 소집허가 신청서)",
    "rcept_no": "20250902900224",
    "flr_nm": "지니틱스",
    "rcept_dt": "20250902",
    "rm": "코"
  },
  {
    "corp_code": "01318933",
    "corp_name": "지니틱스",
    "stock_code": "303030",
    "corp_cls": "K",
    "report_nm": "소송등의제기ㆍ신청(경영권분쟁소송)              (증거보전)",
    "rcept_no": "20250829900609",
    "flr_nm": "지니틱스",
    "rcept_dt": "20250829",
    "rm": "코"
  },
  {
    "corp_code": "01318933",
    "corp_name": "지니틱스",
    "stock_code": "303030",
    "corp_cls": "K",
    "report_nm": "소송등의제기ㆍ신청(경영권분쟁소송)              (이사해임청구)",
    "rcept_no": "20250828900289",
    "flr_nm": "지니틱스",
    "rcept_dt": "20250828",
    "rm": "코"
  },
  {
    "corp_code": "01318933",
    "corp_name": "지니틱스",
    "stock_code": "303030",
    "corp_cls": "K",
    "report_nm": "소송등의제기ㆍ신청(경영권분쟁소송)              (장부등열람허용가처분)",
    "rcept_no": "20250822900229",
    "flr_nm": "지니틱스",
    "rcept_dt": "20250822",
    "rm": "코"
  },
  {
    "corp_code": "01318933",
    "corp_name": "지니틱스",
    "stock_code": "303030",
    "corp_cls": "K",
    "report_nm": "소송등의제기ㆍ신청(경영권분쟁소송)              (주주총회 개최금지 가처분)",
    "rcept_no": "20250822900224",
    "flr_nm": "지니틱스",
    "rcept_dt": "20250822",
    "rm": "코"
  },
  {
    "corp_code": "01318933",
    "corp_name": "지니틱스",
    "stock_code": "303030",
    "corp_cls": "K",
    "report_nm": "[기재정정]주주명부폐쇄기간또는기준일설정              ",
    "rcept_no": "20250821900618",
    "flr_nm": "지니틱스",
    "rcept_dt": "20250821",
    "rm": "코"
  },
  {
    "corp_code": "01318933",
    "corp_name": "지니틱스",
    "stock_code": "303030",
    "corp_cls": "K",
    "report_nm": "[기재정정]주주총회소집결의              (임시주주총회)",
    "rcept_no": "20250821900596",
    "flr_nm": "지니틱스",
    "rcept_dt": "20250821",
    "rm": "코"
  },
  {
    "corp_code": "01318933",
    "corp_name": "지니틱스",
    "stock_code": "303030",
    "corp_cls": "K",
    "report_nm": "소송등의제기ㆍ신청(경영권분쟁소송)              (직무집행정지 및 직무대행자 선임)",
    "rcept_no": "20250821900585",
    "flr_nm": "지니틱스",
    "rcept_dt": "20250821",
    "rm": "코"
  },
  {
    "corp_code": "01318933",
    "corp_name": "지니틱스",
    "stock_code": "303030",
    "corp_cls": "K",
    "report_nm": "주주명부폐쇄기간또는기준일설정              ",
    "rcept_no": "20250819900426",
    "flr_nm": "지니틱스",
    "rcept_dt": "20250819",
    "rm": "코"
  },
  {
    "corp_code": "01318933",
    "corp_name": "지니틱스",
    "stock_code": "303030",
    "corp_cls": "K",
    "report_nm": "주주총회소집결의              (임시주주총회)",
    "rcept_no": "20250819900393",
    "flr_nm": "지니틱스",
    "rcept_dt": "20250819",
    "rm": "코정"
  },
  {
    "corp_code": "01318933",
    "corp_name": "지니틱스",
    "stock_code": "303030",
    "corp_cls": "K",
    "report_nm": "반기보고서 (2025.06)",
    "rcept_no": "20250814002246",
    "flr_nm": "지니틱스",
    "rcept_dt": "20250814",
    "rm": ""
  },
  {
    "corp_code": "01318933",
    "corp_name": "지니틱스",
    "stock_code": "303030",
    "corp_cls": "K",
    "report_nm": "소송등의판결ㆍ결정              (경영권 분쟁 소송)(임시주주총회 소집허가)",
    "rcept_no": "20250814900901",
    "flr_nm": "지니틱스",
    "rcept_dt": "20250814",
    "rm": "코"
  },
  {
    "corp_code": "01318933",
    "corp_name": "지니틱스",
    "stock_code": "303030",
    "corp_cls": "K",
    "report_nm": "주주명부폐쇄기간또는기준일설정              ",
    "rcept_no": "20250812900098",
    "flr_nm": "지니틱스",
    "rcept_dt": "20250812",
    "rm": "코"
  },
  {
    "corp_code": "01318933",
    "corp_name": "지니틱스",
    "stock_code": "303030",
    "corp_cls": "K",
    "report_nm": "주주총회소집결의              (임시주주총회)",
    "rcept_no": "20250812900058",
    "flr_nm": "지니틱스",
    "rcept_dt": "20250812",
    "rm": "코정"
  },
  {
    "corp_code": "01318933",
    "corp_name": "지니틱스",
    "stock_code": "303030",
    "corp_cls": "K",
    "report_nm": "[기재정정]소송등의제기ㆍ신청(경영권분쟁소송)              (임시주주총회 소집허가)",
    "rcept_no": "20250807900580",
    "flr_nm": "지니틱스",
    "rcept_dt": "20250807",
    "rm": "코"
  },
  {
    "corp_code": "01318933",
    "corp_name": "지니틱스",
    "stock_code": "303030",
    "corp_cls": "K",
    "report_nm": "임시주주총회결과              ",
    "rcept_no": "20250723900616",
    "flr_nm": "지니틱스",
    "rcept_dt": "20250723",
    "rm": "코"
  },
  {
    "corp_code": "01318933",
    "corp_name": "지니틱스",
    "stock_code": "303030",
    "corp_cls": "K",
    "report_nm": "[기재정정]주주총회소집공고",
    "rcept_no": "20250723000002",
    "flr_nm": "지니틱스",
    "rcept_dt": "20250723",
    "rm": ""
  },
  {
    "corp_code": "01318933",
    "corp_name": "지니틱스",
    "stock_code": "303030",
    "corp_cls": "K",
    "report_nm": "[기재정정]주주총회소집결의              (임시주주총회)",
    "rcept_no": "20250723900006",
    "flr_nm": "지니틱스",
    "rcept_dt": "20250723",
    "rm": "코"
  },
  {
    "corp_code": "01318933",
    "corp_name": "지니틱스",
    "stock_code": "303030",
    "corp_cls": "K",
    "report_nm": "주주명부폐쇄기간또는기준일설정              ",
    "rcept_no": "20250722900443",
    "flr_nm": "지니틱스",
    "rcept_dt": "20250722",
    "rm": "코정"
  },
  {
    "corp_code": "01318933",
    "corp_name": "지니틱스",
    "stock_code": "303030",
    "corp_cls": "K",
    "report_nm": "[기재정정]주주총회소집공고",
    "rcept_no": "20250722000241",
    "flr_nm": "지니틱스",
    "rcept_dt": "20250722",
    "rm": "정"
  },
  {
    "corp_code": "01318933",
    "corp_name": "지니틱스",
    "stock_code": "303030",
    "corp_cls": "K",
    "report_nm": "주주총회소집결의              (임시주주총회)",
    "rcept_no": "20250722900437",
    "flr_nm": "지니틱스",
    "rcept_dt": "20250722",
    "rm": "코정"
  },
  {
    "corp_code": "01318933",
    "corp_name": "지니틱스",
    "stock_code": "303030",
    "corp_cls": "K",
    "report_nm": "[기재정정]주주총회소집결의              (임시주주총회)",
    "rcept_no": "20250722900427",
    "flr_nm": "지니틱스",
    "rcept_dt": "20250722",
    "rm": "코정"
  },
  {
    "corp_code": "01318933",
    "corp_name": "지니틱스",
    "stock_code": "303030",
    "corp_cls": "K",
    "report_nm": "[기재정정]주주총회소집공고",
    "rcept_no": "20250708000379",
    "flr_nm": "지니틱스",
    "rcept_dt": "20250708",
    "rm": "정"
  },
  {
    "corp_code": "01318933",
    "corp_name": "지니틱스",
    "stock_code": "303030",
    "corp_cls": "K",
    "report_nm": "[기재정정]주주총회소집결의              (임시주주총회)",
    "rcept_no": "20250708900502",
    "flr_nm": "지니틱스",
    "rcept_dt": "20250708",
    "rm": "코정"
  },
  {
    "corp_code": "01318933",
    "corp_name": "지니틱스",
    "stock_code": "303030",
    "corp_cls": "K",
    "report_nm": "[기재정정]소송등의판결ㆍ결정              (의결권행사허용가처분-취하)",
    "rcept_no": "20250704900758",
    "flr_nm": "지니틱스",
    "rcept_dt": "20250704",
    "rm": "코"
  },
  {
    "corp_code": "01318933",
    "corp_name": "지니틱스",
    "stock_code": "303030",
    "corp_cls": "K",
    "report_nm": "소송등의판결ㆍ결정              (경영권 분쟁 소송)(의결권행사허용가처분)",
    "rcept_no": "20250702900389",
    "flr_nm": "지니틱스",
    "rcept_dt": "20250702",
    "rm": "코정"
  },
  {
    "corp_code": "01318933",
    "corp_name": "지니틱스",
    "stock_code": "303030",
    "corp_cls": "K",
    "report_nm": "소송등의판결ㆍ결정              (경영권 분쟁 소송)(검사인선임)",
    "rcept_no": "20250702900388",
    "flr_nm": "지니틱스",
    "rcept_dt": "20250702",
    "rm": "코"
  },
  {
    "corp_code": "01318933",
    "corp_name": "지니틱스",
    "stock_code": "303030",
    "corp_cls": "K",
    "report_nm": "주식등의대량보유상황보고서(일반)",
    "rcept_no": "20250630000597",
    "flr_nm": "헤일로마이크로일렉트로닉스인터내셔널코퍼레이션",
    "rcept_dt": "20250630",
    "rm": ""
  },
  {
    "corp_code": "01318933",
    "corp_name": "지니틱스",
    "stock_code": "303030",
    "corp_cls": "K",
    "report_nm": "임원ㆍ주요주주특정증권등소유상황보고서",
    "rcept_no": "20250627000698",
    "flr_nm": "이유상",
    "rcept_dt": "20250627",
    "rm": ""
  },
  {
    "corp_code": "01318933",
    "corp_name": "지니틱스",
    "stock_code": "303030",
    "corp_cls": "K",
    "report_nm": "주식등의대량보유상황보고서(일반)",
    "rcept_no": "20250620000562",
    "flr_nm": "헤일로마이크로일렉트로닉스인터내셔널코퍼레이션",
    "rcept_dt": "20250620",
    "rm": ""
  },
  {
    "corp_code": "01318933",
    "corp_name": "지니틱스",
    "stock_code": "303030",
    "corp_cls": "K",
    "report_nm": "소액공모실적보고서",
    "rcept_no": "20250620000226",
    "flr_nm": "지니틱스",
    "rcept_dt": "20250620",
    "rm": ""
  },
  {
    "corp_code": "01318933",
    "corp_name": "지니틱스",
    "stock_code": "303030",
    "corp_cls": "K",
    "report_nm": "증권발행결과(자율공시)              ",
    "rcept_no": "20250620900215",
    "flr_nm": "지니틱스",
    "rcept_dt": "20250620",
    "rm": "코"
  },
  {
    "corp_code": "01318933",
    "corp_name": "지니틱스",
    "stock_code": "303030",
    "corp_cls": "K",
    "report_nm": "[기재정정]소송등의제기ㆍ신청(경영권분쟁소송)              (검사인선임)",
    "rcept_no": "20250620900200",
    "flr_nm": "지니틱스",
    "rcept_dt": "20250620",
    "rm": "코"
  },
  {
    "corp_code": "01318933",
    "corp_name": "지니틱스",
    "stock_code": "303030",
    "corp_cls": "K",
    "report_nm": "[기재정정]소송등의제기ㆍ신청(경영권분쟁소송)              (의결권행사허용가처분)",
    "rcept_no": "20250620900145",
    "flr_nm": "지니틱스",
    "rcept_dt": "20250620",
    "rm": "코"
  },
  {
    "corp_code": "01318933",
    "corp_name": "지니틱스",
    "stock_code": "303030",
    "corp_cls": "K",
    "report_nm": "소송등의판결ㆍ결정              (신주발행금지가처분)",
    "rcept_no": "20250619900728",
    "flr_nm": "지니틱스",
    "rcept_dt": "20250619",
    "rm": "코"
  },
  {
    "corp_code": "01318933",
    "corp_name": "지니틱스",
    "stock_code": "303030",
    "corp_cls": "K",
    "report_nm": "유상증자또는주식관련사채등의청약결과(자율공시)              ",
    "rcept_no": "20250618900656",
    "flr_nm": "지니틱스",
    "rcept_dt": "20250618",
    "rm": "코"
  },
  {
    "corp_code": "01318933",
    "corp_name": "지니틱스",
    "stock_code": "303030",
    "corp_cls": "K",
    "report_nm": "소송등의판결ㆍ결정              (장부등열람허용가처분)",
    "rcept_no": "20250618900389",
    "flr_nm": "지니틱스",
    "rcept_dt": "20250618",
    "rm": "코"
  },
  {
    "corp_code": "01318933",
    "corp_name": "지니틱스",
    "stock_code": "303030",
    "corp_cls": "K",
    "report_nm": "[기재정정]의결권대리행사권유참고서류",
    "rcept_no": "20250618000130",
    "flr_nm": "헤일로전자",
    "rcept_dt": "20250618",
    "rm": ""
  },
  {
    "corp_code": "01318933",
    "corp_name": "지니틱스",
    "stock_code": "303030",
    "corp_cls": "K",
    "report_nm": "[첨부정정]의결권대리행사권유참고서류",
    "rcept_no": "20250617000426",
    "flr_nm": "지니틱스",
    "rcept_dt": "20250618",
    "rm": ""
  },
  {
    "corp_code": "01318933",
    "corp_name": "지니틱스",
    "stock_code": "303030",
    "corp_cls": "K",
    "report_nm": "[기재정정]주요사항보고서(소송등의제기)",
    "rcept_no": "20250617000419",
    "flr_nm": "지니틱스",
    "rcept_dt": "20250617",
    "rm": ""
  },
  {
    "corp_code": "01318933",
    "corp_name": "지니틱스",
    "stock_code": "303030",
    "corp_cls": "K",
    "report_nm": "의결권대리행사권유참고서류",
    "rcept_no": "20250617000422",
    "flr_nm": "지니틱스",
    "rcept_dt": "20250617",
    "rm": "정"
  },
  {
    "corp_code": "01318933",
    "corp_name": "지니틱스",
    "stock_code": "303030",
    "corp_cls": "K",
    "report_nm": "[기재정정]주주총회소집공고",
    "rcept_no": "20250617000420",
    "flr_nm": "지니틱스",
    "rcept_dt": "20250617",
    "rm": "정"
  },
  {
    "corp_code": "01318933",
    "corp_name": "지니틱스",
    "stock_code": "303030",
    "corp_cls": "K",
    "report_nm": "[기재정정]주주총회소집결의              (임시주주총회)",
    "rcept_no": "20250617900495",
    "flr_nm": "지니틱스",
    "rcept_dt": "20250617",
    "rm": "코정"
  },
  {
    "corp_code": "01318933",
    "corp_name": "지니틱스",
    "stock_code": "303030",
    "corp_cls": "K",
    "report_nm": "주요사항보고서(소송등의제기)",
    "rcept_no": "20250617000321",
    "flr_nm": "지니틱스",
    "rcept_dt": "20250617",
    "rm": "정"
  },
  {
    "corp_code": "01318933",
    "corp_name": "지니틱스",
    "stock_code": "303030",
    "corp_cls": "K",
    "report_nm": "소송등의제기ㆍ신청(경영권분쟁소송)              (검사인선임)",
    "rcept_no": "20250617900279",
    "flr_nm": "지니틱스",
    "rcept_dt": "20250617",
    "rm": "코정"
  },
  {
    "corp_code": "01318933",
    "corp_name": "지니틱스",
    "stock_code": "303030",
    "corp_cls": "K",
    "report_nm": "[첨부정정]의결권대리행사권유참고서류",
    "rcept_no": "20250617000196",
    "flr_nm": "헤일로전자",
    "rcept_dt": "20250617",
    "rm": "정"
  },
  {
    "corp_code": "01318933",
    "corp_name": "지니틱스",
    "stock_code": "303030",
    "corp_cls": "K",
    "report_nm": "[기재정정]소액공모공시서류(지분증권)",
    "rcept_no": "20250616000332",
    "flr_nm": "지니틱스",
    "rcept_dt": "20250616",
    "rm": ""
  },
  {
    "corp_code": "01318933",
    "corp_name": "지니틱스",
    "stock_code": "303030",
    "corp_cls": "K",
    "report_nm": "[기재정정]주요사항보고서(유상증자결정)",
    "rcept_no": "20250616000316",
    "flr_nm": "지니틱스",
    "rcept_dt": "20250616",
    "rm": ""
  },
  {
    "corp_code": "01318933",
    "corp_name": "지니틱스",
    "stock_code": "303030",
    "corp_cls": "K",
    "report_nm": "[기재정정]의결권대리행사권유참고서류",
    "rcept_no": "20250616000318",
    "flr_nm": "헤일로전자",
    "rcept_dt": "20250616",
    "rm": "정"
  },
  {
    "corp_code": "01318933",
    "corp_name": "지니틱스",
    "stock_code": "303030",
    "corp_cls": "K",
    "report_nm": "소송등의제기ㆍ신청(경영권분쟁소송)              (의결권행사허용가처분)",
    "rcept_no": "20250616900411",
    "flr_nm": "지니틱스",
    "rcept_dt": "20250616",
    "rm": "코정"
  },
  {
    "corp_code": "01318933",
    "corp_name": "지니틱스",
    "stock_code": "303030",
    "corp_cls": "K",
    "report_nm": "유상증자최종발행가액확정              (일반공모-소액공모)",
    "rcept_no": "20250613900743",
    "flr_nm": "지니틱스",
    "rcept_dt": "20250613",
    "rm": "코"
  },
  {
    "corp_code": "01318933",
    "corp_name": "지니틱스",
    "stock_code": "303030",
    "corp_cls": "K",
    "report_nm": "[기재정정]소액공모공시서류(지분증권)",
    "rcept_no": "20250613000507",
    "flr_nm": "지니틱스",
    "rcept_dt": "20250613",
    "rm": "정"
  },
  {
    "corp_code": "01318933",
    "corp_name": "지니틱스",
    "stock_code": "303030",
    "corp_cls": "K",
    "report_nm": "의결권대리행사권유참고서류",
    "rcept_no": "20250613000498",
    "flr_nm": "헤일로전자",
    "rcept_dt": "20250613",
    "rm": "정"
  },
  {
    "corp_code": "01318933",
    "corp_name": "지니틱스",
    "stock_code": "303030",
    "corp_cls": "K",
    "report_nm": "[기재정정]주요사항보고서(유상증자결정)",
    "rcept_no": "20250613000476",
    "flr_nm": "지니틱스",
    "rcept_dt": "20250613",
    "rm": "정"
  },
  {
    "corp_code": "01318933",
    "corp_name": "지니틱스",
    "stock_code": "303030",
    "corp_cls": "K",
    "report_nm": "[기재정정]소액공모공시서류(지분증권)",
    "rcept_no": "20250612000479",
    "flr_nm": "지니틱스",
    "rcept_dt": "20250613",
    "rm": "정"
  },
  {
    "corp_code": "01318933",
    "corp_name": "지니틱스",
    "stock_code": "303030",
    "corp_cls": "K",
    "report_nm": "[기재정정]주요사항보고서(유상증자결정)",
    "rcept_no": "20250612000357",
    "flr_nm": "지니틱스",
    "rcept_dt": "20250612",
    "rm": "정"
  },
  {
    "corp_code": "01318933",
    "corp_name": "지니틱스",
    "stock_code": "303030",
    "corp_cls": "K",
    "report_nm": "[기재정정]소액공모공시서류(지분증권)",
    "rcept_no": "20250611000418",
    "flr_nm": "지니틱스",
    "rcept_dt": "20250611",
    "rm": "정"
  },
  {
    "corp_code": "01318933",
    "corp_name": "지니틱스",
    "stock_code": "303030",
    "corp_cls": "K",
    "report_nm": "[기재정정]주요사항보고서(유상증자결정)",
    "rcept_no": "20250611000339",
    "flr_nm": "지니틱스",
    "rcept_dt": "20250611",
    "rm": "정"
  },
  {
    "corp_code": "01318933",
    "corp_name": "지니틱스",
    "stock_code": "303030",
    "corp_cls": "K",
    "report_nm": "소액공모공시서류(지분증권)",
    "rcept_no": "20250611000001",
    "flr_nm": "지니틱스",
    "rcept_dt": "20250611",
    "rm": "정"
  },
  {
    "corp_code": "01318933",
    "corp_name": "지니틱스",
    "stock_code": "303030",
    "corp_cls": "K",
    "report_nm": "주요사항보고서(유상증자결정)",
    "rcept_no": "20250610000454",
    "flr_nm": "지니틱스",
    "rcept_dt": "20250611",
    "rm": "정"
  },
  {
    "corp_code": "01318933",
    "corp_name": "지니틱스",
    "stock_code": "303030",
    "corp_cls": "K",
    "report_nm": "주주총회소집공고",
    "rcept_no": "20250610000332",
    "flr_nm": "지니틱스",
    "rcept_dt": "20250610",
    "rm": "정"
  },
  {
    "corp_code": "01318933",
    "corp_name": "지니틱스",
    "stock_code": "303030",
    "corp_cls": "K",
    "report_nm": "소송등의제기ㆍ신청(경영권분쟁소송)              (장부등열람허용가처분)",
    "rcept_no": "20250605900481",
    "flr_nm": "지니틱스",
    "rcept_dt": "20250605",
    "rm": "코"
  },
  {
    "corp_code": "01318933",
    "corp_name": "지니틱스",
    "stock_code": "303030",
    "corp_cls": "K",
    "report_nm": "임원ㆍ주요주주특정증권등소유상황보고서",
    "rcept_no": "20250530001872",
    "flr_nm": "권석만",
    "rcept_dt": "20250530",
    "rm": ""
  },
  {
    "corp_code": "01318933",
    "corp_name": "지니틱스",
    "stock_code": "303030",
    "corp_cls": "K",
    "report_nm": "분기보고서 (2025.03)",
    "rcept_no": "20250514001041",
    "flr_nm": "지니틱스",
    "rcept_dt": "20250514",
    "rm": ""
  },
  {
    "corp_code": "01318933",
    "corp_name": "지니틱스",
    "stock_code": "303030",
    "corp_cls": "K",
    "report_nm": "주주명부폐쇄기간또는기준일설정              ",
    "rcept_no": "20250514900766",
    "flr_nm": "지니틱스",
    "rcept_dt": "20250514",
    "rm": "코"
  },
  {
    "corp_code": "01318933",
    "corp_name": "지니틱스",
    "stock_code": "303030",
    "corp_cls": "K",
    "report_nm": "주주총회소집결의              (임시주주총회)",
    "rcept_no": "20250423900400",
    "flr_nm": "지니틱스",
    "rcept_dt": "20250423",
    "rm": "코정"
  },
  {
    "corp_code": "01318933",
    "corp_name": "지니틱스",
    "stock_code": "303030",
    "corp_cls": "K",
    "report_nm": "소송등의제기ㆍ신청(경영권분쟁소송)              (임시주주총회 소집허가)",
    "rcept_no": "20250411900777",
    "flr_nm": "지니틱스",
    "rcept_dt": "20250411",
    "rm": "코정"
  },
  {
    "corp_code": "01318933",
    "corp_name": "지니틱스",
    "stock_code": "303030",
    "corp_cls": "K",
    "report_nm": "주식매수선택권부여에관한신고",
    "rcept_no": "20250326001187",
    "flr_nm": "지니틱스",
    "rcept_dt": "20250326",
    "rm": "정"
  },
  {
    "corp_code": "01318933",
    "corp_name": "지니틱스",
    "stock_code": "303030",
    "corp_cls": "K",
    "report_nm": "[기재정정]주식매수선택권부여에관한신고",
    "rcept_no": "20250326001177",
    "flr_nm": "지니틱스",
    "rcept_dt": "20250326",
    "rm": ""
  },
  {
    "corp_code": "01318933",
    "corp_name": "지니틱스",
    "stock_code": "303030",
    "corp_cls": "K",
    "report_nm": "정기주주총회결과              ",
    "rcept_no": "20250326902379",
    "flr_nm": "지니틱스",
    "rcept_dt": "20250326",
    "rm": "코"
  },
  {
    "corp_code": "01318933",
    "corp_name": "지니틱스",
    "stock_code": "303030",
    "corp_cls": "K",
    "report_nm": "사업보고서 (2024.12)",
    "rcept_no": "20250318000359",
    "flr_nm": "지니틱스",
    "rcept_dt": "20250318",
    "rm": ""
  },
  {
    "corp_code": "01318933",
    "corp_name": "지니틱스",
    "stock_code": "303030",
    "corp_cls": "K",
    "report_nm": "감사보고서제출              ",
    "rcept_no": "20250311900887",
    "flr_nm": "지니틱스",
    "rcept_dt": "20250311",
    "rm": "코"
  },
  {
    "corp_code": "01318933",
    "corp_name": "지니틱스",
    "stock_code": "303030",
    "corp_cls": "K",
    "report_nm": "주주총회소집공고",
    "rcept_no": "20250311000257",
    "flr_nm": "지니틱스",
    "rcept_dt": "20250311",
    "rm": ""
  },
  {
    "corp_code": "01318933",
    "corp_name": "지니틱스",
    "stock_code": "303030",
    "corp_cls": "K",
    "report_nm": "주주총회소집결의              ",
    "rcept_no": "20250304900903",
    "flr_nm": "지니틱스",
    "rcept_dt": "20250304",
    "rm": "코"
  },
  {
    "corp_code": "01318933",
    "corp_name": "지니틱스",
    "stock_code": "303030",
    "corp_cls": "K",
    "report_nm": "매출액또는손익구조30%(대규모법인은15%)이상변동              ",
    "rcept_no": "20250204900548",
    "flr_nm": "지니틱스",
    "rcept_dt": "20250204",
    "rm": "코"
  },
  {
    "corp_code": "01318933",
    "corp_name": "지니틱스",
    "stock_code": "303030",
    "corp_cls": "K",
    "report_nm": "주식등의대량보유상황보고서(일반)",
    "rcept_no": "20250103000282",
    "flr_nm": "헤일로마이크로일렉트로닉스인터내셔널코퍼레이션",
    "rcept_dt": "20250103",
    "rm": ""
  },
  {
    "corp_code": "01318933",
    "corp_name": "지니틱스",
    "stock_code": "303030",
    "corp_cls": "K",
    "report_nm": "임원ㆍ주요주주특정증권등소유상황보고서",
    "rcept_no": "20250103000246",
    "flr_nm": "헤일로마이크로일렉트로닉스인터내셔널코퍼레이션",
    "rcept_dt": "20250103",
    "rm": ""
  }
]